sco_py/expr.py
sco_py/sco_gurobi/__init__.py
sco_py/sco_gurobi/prob.py
sco_py/sco_gurobi/solver.py
sco_py/sco_gurobi/variable.py
sco_py/sco_osqp/__init__.py
sco_py/sco_osqp/osqp_utils.py
sco_py/sco_osqp/prob.py
sco_py/sco_osqp/solver.py
sco_py/sco_osqp/variable.py
sco_py-0.4.0.dist-info/LICENSE
sco_py-0.4.0.dist-info/WHEEL
sco_py-0.4.0.dist-info/METADATA
sco_py-0.4.0.dist-info/RECORD
