Metadata-Version: 2.1
Name: sco-py
Version: 0.4.0
Summary: A Sequential Convex Optimization library for solving non-convex optimization problems. Intended for use with the OpenTAMP planning system.
License: MIT
Author: Nishanth Kumar
Author-email: njk@csail.mit.edu
Requires-Python: >=3.7,<3.11
Classifier: License :: OSI Approved :: MIT License
Classifier: Programming Language :: Python :: 3
Classifier: Programming Language :: Python :: 3.10
Classifier: Programming Language :: Python :: 3.7
Classifier: Programming Language :: Python :: 3.8
Classifier: Programming Language :: Python :: 3.9
Provides-Extra: gurobi
Requires-Dist: gurobipy (>=9.0.0); extra == "gurobi"
Requires-Dist: numdifftools (>=0.9.40,<0.10.0)
Requires-Dist: numpy (>=1.21.4,<2.0.0)
Requires-Dist: osqp (>=0.6.2,<0.7.0)
Requires-Dist: pytest (>=6.2.5,<7.0.0)
Requires-Dist: scipy (>=1.7.2,<2.0.0)
